[
    {
        "name": "First Amendment",
        "id": "first",
        "theme": "green",
        "quizzes": [
            {
                "type": "multi-select",
                "question": "Which freedoms are given by the Fist Amendment?",
                "options": [
                    "Freedom of Movement",
                    "Freedom of Religion",
                    "Right to a Fair Trial",
                    "Freedom of Speech",
                    "Freedom of Expression",
                    "Freedom to Murder",
                    "Freedom of Assembly",
                    "Right to Petition"
                ],
                "answer": [1,3,4,6,7]
            },
            {
                "type": "true-false",
                "question": "Telling lies about someone is protected by the First Amendment.",
                "answer": false
            },
            {
                "type": "true-false",
                "question": "Your parents can force you to practice a certain religion.",
                "answer": false
            },
            {
                "type": "four-quarter",
                "question": "What is not protected by the First Amendment?",
                "options": [
                    "Burning an American flag that belongs to you",
                    "Wearing a shirt with a slogan that may offend some people",
                    "Saying something mean about your Social Studies teacher",
                    "Protesting a law in a peaceful march"
                ],
                "answer": [2]
            }
        ]
    },
    {
        "name": "Second and Third Amendments",
        "id": "secondThird",
        "theme": "yellow",
        "quizzes": [
            {
                "type": "fill-blank",
                "question": "Finish the first sentence of the Second Amendment",
				"start": "A well regulated",
				"end": ", being necessary to the security of a free State, the right of the people to keep and bear Arms, shall not be infringed.",
                "answer": "Militia"
            },
            {
                "type": "true-false",
                "question": "State and local governments have the right to limit the Second Amendment",
                "answer": true
            },
            {
                "type": "true-false",
                "question": "The government has the right to place soldiers in your home during a war",
                "answer": false
            },
            {
                "type": "picker",
                "question": "In how many court cases has the Third Amendment been the primary basis?",
                "min": 0,
				"max": 10,
                "answer": 0
            }
        ]
    },
    {
        "name": "Fourth and Fifth Amendments",
        "id": "fourthFifth",
        "theme": "blue",
        "quizzes": [
            {
                "type": "true-false",
                "question": "Police always need a search warrant to search your belongings",
                "answer": false
            },
            {
                "type": "four-quarter",
                "question": "What type of search is not protected by the Fourth Amendment?",
                "options": [
                    "School silently installing spyware on your phone when you connect to their Wi-Fi network",
                    "School searching your backpack when it is in your locker",
                    "Police entering your home simply because you have a car that would make a good addition to the police's fleet",
                    "Police officer telling you to take off your shirt to see a really cool tatoo that you have"
                ],
                "answer": [0]
            },
            {
                "type": "true-false",
                "question": "The city can destroy your house without prior notice and compensation if they want to build a road there",
                "answer": false
            },
            {
                "type": "true-false",
                "question": "You can be forced to unlock your phone for a trial if you are using a face or fingerprint unlock.",
                "answer": true
            }
        ]
    },
    {
        "name": "Sixth and Seventh Amendments",
        "id": "sixthSeventh",
        "theme": "red",
        "quizzes": [
            {
                "type": "fill-blank",
                "question": "Finish the sentence:",
                "start": "In all criminal prosecutions, the accused shall enjoy the right to a speedy and",
				"end": ".",
                "answer": "public trial"
            },
            {
                "type": "true-false",
                "question": "The government has to provide you with a lawyer",
				"answer": true
            },
            {
                "type": "picker",
                "question": "You have the right to a jury if the value in controversy is more than (dollars)",
				"min": 0,
				"max": 100,
				"step": 5,
                "answer": 20
            },
            {
                "type": "picker",
                "question": "What is the minimum amount of members in a jury",
                "min": 1,
                "max": 12,
                "answer": 6
            }
        ]
    },
    {
        "name": "Eighth Amendment",
        "id": "eighth",
        "theme": "green",
        "quizzes": [
            {
                "type": "fill-two-blanks",
                "question": "What are the protections of the Eighth Amendment?",
                "answer": [
					"excessive bail",
					"cruel and unusual punishment"
				]
            },
            {
                "type": "true-false",
                "question": "Does capital punishment (death penalty) count as cruel and unusual punishment as long as it is standardized?",
                "answer": false
            },
            {
                "type": "fill-blank",
                "question": "What amount of money counts as 'excessive' bail? Put either an amount or 'undefined' as your answer",
                "start": "$",
                "answer": "undefined"
            },
            {
                "type": "picker",
                "question": "What is the minimum age at which the death penalty is allowed (and not curuel and unusual punishment)?",
                "min": 0,
                "max": 20,
                "step": 2,
                "answer": 18
            }
        ]
    },
    {
        "name": "Ninth and Tenth Amendments",
        "id": "ninthTenth",
        "theme": "purple",
        "quizzes": [
            {
                "type": "true-false",
                "question": "Anything not stated in the Constitution or regulated by your state is legal",
                "answer": true
            },
            {
                "type": "fill-blank",
                "question": "Finish the text of the Ninth Amendment",
                "start": "The enumeration in the Constitution, of certain rights, shall not be construed to deny or disparage others",
                "end": ".",
                "answer": "retained by the people"
            },
            {
                "type": "single-select",
                "question": "Which group was in support of the Tenth Amendment?",
                "options": [
                    "Federalists",
                    "Antifederalists",
                ],
                "answer": [1]
            },
            {
                "type": "fill-two-blanks",
                "question": "Powers not given to the national government by the Constitution are given to whom?",
                "answer": [
            		"the states",
            		"the people"
                ]
            }
        ]
    }
]
